splines/__init__.py
splines/metrics.py
splines/regression.py
splines/core/__init__.py
splines/core/mv_splines.py
splines/core/optimizers.py
splines/core/training_algorithms.py
splines/core/utils.py
splines/core/uv_splines.py
fksplines-0.6.1.dist-info/LICENSE
fksplines-0.6.1.dist-info/METADATA
fksplines-0.6.1.dist-info/WHEEL
fksplines-0.6.1.dist-info/top_level.txt
fksplines-0.6.1.dist-info/RECORD
