Metadata-Version: 2.1
Name: fksplines
Version: 0.6.1
Summary: A package to do uni-variate and multi-variate free-knot spline regression.
Home-page: https://github.com/ged1182/splines
Author: George Dekermenjian
Author-email: ged1182@gmail.com
License: MIT License
Platform: UNKNOWN
Classifier: Programming Language :: Python :: 3
Classifier: License :: OSI Approved :: MIT License
Classifier: Operating System :: OS Independent
Requires-Python: >=3.7
